PiWarsTurkiyeRobotKiti2019/HizlandirilmisPiKamera.py
PiWarsTurkiyeRobotKiti2019/Kumanda.py
PiWarsTurkiyeRobotKiti2019/MotorKontrol.py
PiWarsTurkiyeRobotKiti2019/ServoKontrol.py
PiWarsTurkiyeRobotKiti2019/UltrasonikSensoru.py
PiWarsTurkiyeRobotKiti2019/__init__.py
PiWarsTurkiyeRobotKiti2019-1.1.3.dist-info/METADATA
PiWarsTurkiyeRobotKiti2019-1.1.3.dist-info/WHEEL
PiWarsTurkiyeRobotKiti2019-1.1.3.dist-info/top_level.txt
PiWarsTurkiyeRobotKiti2019-1.1.3.dist-info/RECORD
