Metadata-Version: 2.1
Name: PiWarsTurkiyeRobotKiti2019
Version: 1.1.3
Summary: Library that makes use of sensors, motors, and servos in the PiWars Turkey robot kit by HisarCS
Home-page: UNKNOWN
Author: Yasar İdikut, Sarp Yoel Kastro
Author-email: yasar.idikut@hisarschool.k12.tr, sarp.kastro@hisarschool.k12.tr
License: UNKNOWN
Platform: UNKNOWN
Classifier: Development Status :: 4 - Beta
Requires-Dist: picamera
Requires-Dist: pygame
Requires-Dist: pololu-drv8835-rpi
Requires-Dist: RPi.GPIO
Requires-Dist: wiringpi
